{
  "$schema": "https://design-tokens.github.io/community-group/format/",
  "$metadata": {
    "project": "MoradBot",
    "version": "1.2",
    "mode": "light",
    "date": "2026-03-01"
  },

  "color": {
    "primary": {
      "50":  { "$value": "#EFF6FF", "$type": "color" },
      "100": { "$value": "#DBEAFE", "$type": "color" },
      "200": { "$value": "#BFDBFE", "$type": "color" },
      "300": { "$value": "#93C5FD", "$type": "color" },
      "400": { "$value": "#60A5FA", "$type": "color" },
      "500": { "$value": "#2281F8", "$type": "color", "$description": "Base primary blue — ثابت رسمياً" },
      "600": { "$value": "#1A6FD4", "$type": "color" },
      "700": { "$value": "#155CB0", "$type": "color" },
      "800": { "$value": "#104A8C", "$type": "color" },
      "900": { "$value": "#0C3868", "$type": "color" }
    },
    "secondary": {
      "50":  { "$value": "#F5F0FD", "$type": "color" },
      "100": { "$value": "#EDE0FB", "$type": "color" },
      "200": { "$value": "#D9C0F7", "$type": "color" },
      "300": { "$value": "#C49BF1", "$type": "color" },
      "400": { "$value": "#B071E8", "$type": "color" },
      "500": { "$value": "#9B51E0", "$type": "color", "$description": "Base secondary purple — ثابت رسمياً" },
      "600": { "$value": "#7E3CB8", "$type": "color" },
      "700": { "$value": "#632E91", "$type": "color" },
      "800": { "$value": "#4A226C", "$type": "color" },
      "900": { "$value": "#321748", "$type": "color" }
    },
    "neutral": {
      "50":    { "$value": "#F8FAFC", "$type": "color" },
      "100":   { "$value": "#F1F5F9", "$type": "color", "$description": "Cool Slate — page background" },
      "200":   { "$value": "#E2E8F0", "$type": "color" },
      "300":   { "$value": "#CBD5E1", "$type": "color" },
      "400":   { "$value": "#94A3B8", "$type": "color" },
      "500":   { "$value": "#64748B", "$type": "color" },
      "600":   { "$value": "#475569", "$type": "color", "$description": "Text secondary" },
      "700":   { "$value": "#334155", "$type": "color" },
      "800":   { "$value": "#1E293B", "$type": "color", "$description": "Text primary" },
      "900":   { "$value": "#0F172A", "$type": "color" },
      "black": { "$value": "#020617", "$type": "color", "$description": "Headings, active nav" },
      "white": { "$value": "#FFFFFF", "$type": "color", "$description": "Card surface, pure white" }
    },
    "success": {
      "light": { "$value": "#D1FAE5", "$type": "color" },
      "base":  { "$value": "#10B981", "$type": "color" },
      "dark":  { "$value": "#059669", "$type": "color" }
    },
    "warning": {
      "light": { "$value": "#FEF3C7", "$type": "color" },
      "base":  { "$value": "#F59E0B", "$type": "color" },
      "dark":  { "$value": "#D97706", "$type": "color" }
    },
    "error": {
      "light": { "$value": "#FEE2E2", "$type": "color" },
      "base":  { "$value": "#EF4444", "$type": "color" },
      "dark":  { "$value": "#DC2626", "$type": "color" }
    },
    "info": {
      "light": { "$value": "#DBEAFE", "$type": "color" },
      "base":  { "$value": "#60A5FA", "$type": "color" },
      "dark":  { "$value": "#2281F8", "$type": "color" }
    },
    "data": {
      "1": { "$value": "#2281F8", "$type": "color" },
      "2": { "$value": "#9B51E0", "$type": "color" },
      "3": { "$value": "#10B981", "$type": "color" },
      "4": { "$value": "#F59E0B", "$type": "color" },
      "5": { "$value": "#EF4444", "$type": "color" },
      "neutral": { "$value": "#94A3B8", "$type": "color" }
    }
  },

  "typography": {
    "fontFamily": {
      "primary": { "$value": "IBM Plex Sans Arabic, system-ui, sans-serif", "$type": "fontFamily", "$description": "Primary Arabic font via Google Fonts" },
      "mono":     { "$value": "JetBrains Mono, Courier New, monospace", "$type": "fontFamily" }
    },
    "fontSize": {
      "display":  { "$value": "48", "$type": "dimension" },
      "h1":       { "$value": "36", "$type": "dimension" },
      "h2":       { "$value": "28", "$type": "dimension" },
      "h3":       { "$value": "22", "$type": "dimension" },
      "h4":       { "$value": "18", "$type": "dimension" },
      "h5":       { "$value": "16", "$type": "dimension" },
      "bodyLg":   { "$value": "18", "$type": "dimension" },
      "body":     { "$value": "16", "$type": "dimension" },
      "bodySm":   { "$value": "14", "$type": "dimension" },
      "caption":  { "$value": "12", "$type": "dimension" },
      "overline": { "$value": "11", "$type": "dimension" },
      "stat":     { "$value": "32", "$type": "dimension" }
    },
    "fontWeight": {
      "regular":  { "$value": "400", "$type": "fontWeight" },
      "medium":   { "$value": "500", "$type": "fontWeight" },
      "semibold": { "$value": "600", "$type": "fontWeight" },
      "bold":     { "$value": "700", "$type": "fontWeight" }
    },
    "lineHeight": {
      "tight":    { "$value": "1.25", "$type": "number" },
      "snug":     { "$value": "1.35", "$type": "number" },
      "normal":   { "$value": "1.5",  "$type": "number" },
      "relaxed":  { "$value": "1.65", "$type": "number" },
      "loose":    { "$value": "1.75", "$type": "number" }
    }
  },

  "spacing": {
    "0":  { "$value": "0",  "$type": "dimension" },
    "1":  { "$value": "4",  "$type": "dimension" },
    "2":  { "$value": "8",  "$type": "dimension" },
    "3":  { "$value": "12", "$type": "dimension" },
    "4":  { "$value": "16", "$type": "dimension" },
    "5":  { "$value": "20", "$type": "dimension" },
    "6":  { "$value": "24", "$type": "dimension" },
    "8":  { "$value": "32", "$type": "dimension" },
    "10": { "$value": "40", "$type": "dimension" },
    "12": { "$value": "48", "$type": "dimension" },
    "16": { "$value": "64", "$type": "dimension" },
    "20": { "$value": "80", "$type": "dimension" },
    "24": { "$value": "96", "$type": "dimension" }
  },

  "borderRadius": {
    "none": { "$value": "0",    "$type": "dimension" },
    "sm":   { "$value": "4",    "$type": "dimension" },
    "md":   { "$value": "8",    "$type": "dimension" },
    "lg":   { "$value": "12",   "$type": "dimension" },
    "xl":   { "$value": "16",   "$type": "dimension" },
    "2xl":  { "$value": "24",   "$type": "dimension" },
    "full": { "$value": "9999", "$type": "dimension" }
  },

  "shadow": {
    "none": { "$value": "none", "$type": "shadow" },
    "xs":   { "$value": "0 1px 2px rgba(0,0,0,0.04)",   "$type": "shadow" },
    "sm":   { "$value": "0 2px 4px rgba(0,0,0,0.05)",   "$type": "shadow" },
    "md":   { "$value": "0 4px 12px rgba(0,0,0,0.06)",  "$type": "shadow" },
    "lg":   { "$value": "0 8px 24px rgba(0,0,0,0.08)",  "$type": "shadow" },
    "xl":   { "$value": "0 16px 40px rgba(0,0,0,0.10)", "$type": "shadow" }
  },

  "duration": {
    "fast":   { "$value": "100ms", "$type": "duration" },
    "normal": { "$value": "200ms", "$type": "duration" },
    "slow":   { "$value": "300ms", "$type": "duration" },
    "slower": { "$value": "500ms", "$type": "duration" }
  },

  "size": {
    "sidebar":    { "$value": "280",  "$type": "dimension" },
    "widget":     { "$value": "380",  "$type": "dimension" },
    "maxContent": { "$value": "1440", "$type": "dimension" },
    "button": {
      "sm": { "$value": "32", "$type": "dimension" },
      "md": { "$value": "40", "$type": "dimension" },
      "lg": { "$value": "48", "$type": "dimension" },
      "xl": { "$value": "56", "$type": "dimension" }
    },
    "input": {
      "sm": { "$value": "32", "$type": "dimension" },
      "md": { "$value": "40", "$type": "dimension" },
      "lg": { "$value": "48", "$type": "dimension" }
    }
  }
}
